{
"type": "FeatureCollection",
"name": "acerola",
"crs": { "type": "name", "properties": { "name": "urn:ogc:def:crs:OGC:1.3:CRS84" } },
"features": [
{ "type": "Feature", "properties": { "type": "acerola" }, "geometry": { "type": "Point", "coordinates": [ -43.440876828121233, -22.639605584097499 ] } }
]
}
