{
"type": "FeatureCollection",
"name": "milho",
"crs": { "type": "name", "properties": { "name": "urn:ogc:def:crs:OGC:1.3:CRS84" } },
"features": [
{ "type": "Feature", "properties": { "type": "milho" }, "geometry": { "type": "Point", "coordinates": [ -43.439730190175979, -22.640660981256072 ] } },
{ "type": "Feature", "properties": { "type": "milho" }, "geometry": { "type": "Point", "coordinates": [ -43.390402969688452, -22.65883151581971 ] } }
]
}
